README.md
setup.py
imojify/__init__.py
imojify/emoji_dictionaries.py
imojify/imojify.py
imojify.egg-info/PKG-INFO
imojify.egg-info/SOURCES.txt
imojify.egg-info/dependency_links.txt
imojify.egg-info/requires.txt
imojify.egg-info/top_level.txt
imojify/Images/1st_place_medal.png
imojify/Images/2nd_place_medal.png
imojify/Images/3rd_place_medal.png
imojify/Images/Empty.png
imojify/Images/a_button_(blood_type).png
imojify/Images/ab_button_(blood_type).png
imojify/Images/abacus.png
imojify/Images/accordion.png
imojify/Images/adhesive_bandage.png
imojify/Images/admission_tickets.png
imojify/Images/aerial_tramway.png
imojify/Images/airplane.png
imojify/Images/airplane_arrival.png
imojify/Images/airplane_departure.png
imojify/Images/alarm_clock.png
imojify/Images/alembic.png
imojify/Images/alien.png
imojify/Images/alien_monster.png
imojify/Images/ambulance.png
imojify/Images/american_football.png
imojify/Images/amphora.png
imojify/Images/anatomical_heart.png
imojify/Images/anchor.png
imojify/Images/anger_symbol.png
imojify/Images/angry_face.png
imojify/Images/angry_face_with_horns.png
imojify/Images/anguished_face.png
imojify/Images/ant.png
imojify/Images/antenna_bars.png
imojify/Images/anxious_face_with_sweat.png
imojify/Images/aquarius.png
imojify/Images/aries.png
imojify/Images/articulated_lorry.png
imojify/Images/artist.png
imojify/Images/artist_dark_skin_tone.png
imojify/Images/artist_light_skin_tone.png
imojify/Images/artist_medium-dark_skin_tone.png
imojify/Images/artist_medium-light_skin_tone.png
imojify/Images/artist_medium_skin_tone.png
imojify/Images/artist_palette.png
imojify/Images/astonished_face.png
imojify/Images/astronaut.png
imojify/Images/astronaut_dark_skin_tone.png
imojify/Images/astronaut_light_skin_tone.png
imojify/Images/astronaut_medium-dark_skin_tone.png
imojify/Images/astronaut_medium-light_skin_tone.png
imojify/Images/astronaut_medium_skin_tone.png
imojify/Images/atm_sign.png
imojify/Images/atom_symbol.png
imojify/Images/auto_rickshaw.png
imojify/Images/automobile.png
imojify/Images/avocado.png
imojify/Images/axe.png
imojify/Images/b_button_(blood_type).png
imojify/Images/baby.png
