Metadata-Version: 2.1
Name: imojify
Version: 0.1.0
Summary: a python library that imagify emoji-unicode
Home-page: UNKNOWN
Author: Abdul-Rahman Khayyal
License: MIT
Platform: UNKNOWN
Classifier: Intended Audience :: Developers
Classifier: Programming Language :: Python
Classifier: Programming Language :: Python :: 3
Classifier: Programming Language :: Python :: 3.6
Classifier: Programming Language :: Python :: 3.7
Classifier: Programming Language :: Python :: 3.8
Classifier: Programming Language :: Python :: 3.9
Classifier: Operating System :: OS Independent
